dmf_control_board_firmware/__init__.py
dmf_control_board_firmware/__init__.pyc
dmf_control_board_firmware/dmf_control_board_base.pyd
dmf_control_board_firmware/libboost_python-mgw44-mt-1_46_1.dll
dmf_control_board_firmware/mingwm10.dll
dmf_control_board_firmware/bin/__init__.py
dmf_control_board_firmware/bin/__init__.pyc
dmf_control_board_firmware/bin/upload.py
dmf_control_board_firmware/calibrate/__init__.py
dmf_control_board_firmware/calibrate/__init__.pyc
dmf_control_board_firmware/calibrate/feedback.py
dmf_control_board_firmware/calibrate/feedback.pyc
dmf_control_board_firmware/calibrate/hv_attenuator.py
dmf_control_board_firmware/calibrate/hv_attenuator.pyc
dmf_control_board_firmware/calibrate/impedance.py
dmf_control_board_firmware/calibrate/impedance.pyc
dmf_control_board_firmware/calibrate/impedance_benchmarks.py
dmf_control_board_firmware/calibrate/impedance_benchmarks.pyc
dmf_control_board_firmware/calibrate/oscope.py
dmf_control_board_firmware/calibrate/oscope.pyc
dmf_control_board_firmware/chip_test/__init__.py
dmf_control_board_firmware/chip_test/__init__.pyc
dmf_control_board_firmware/chip_test/plot.py
dmf_control_board_firmware/driver/arduino.cat
dmf_control_board_firmware/driver/arduino.inf
dmf_control_board_firmware/firmware/mega2560/1_1/dmf_control_board.hex
dmf_control_board_firmware/firmware/mega2560/1_2/dmf_control_board.hex
dmf_control_board_firmware/firmware/mega2560/1_3/dmf_control_board.hex
dmf_control_board_firmware/firmware/mega2560/2_0/dmf_control_board.hex
dmf_control_board_firmware/firmware/mega2560/2_1/dmf_control_board.hex
dmf_control_board_firmware/gui/__init__.py
dmf_control_board_firmware/gui/__init__.pyc
dmf_control_board_firmware/gui/channels.py
dmf_control_board_firmware/gui/channels.pyc
dmf_control_board_firmware/gui/channels_intro.png
dmf_control_board_firmware/gui/channels_intro.svg
dmf_control_board_firmware/gui/impedance.py
dmf_control_board_firmware/gui/impedance.pyc
wheeler.dmf_control_board_firmware-1.4.post4.dist-info/DESCRIPTION.rst
wheeler.dmf_control_board_firmware-1.4.post4.dist-info/METADATA
wheeler.dmf_control_board_firmware-1.4.post4.dist-info/RECORD
wheeler.dmf_control_board_firmware-1.4.post4.dist-info/WHEEL
wheeler.dmf_control_board_firmware-1.4.post4.dist-info/metadata.json
wheeler.dmf_control_board_firmware-1.4.post4.dist-info/top_level.txt
