Metadata-Version: 2.0
Name: wheeler.dmf-control-board-firmware
Version: 1.4.post4
Summary: Arduino-based DMF control board firmware and Python API.
Home-page: https://github.com/wheeler-microfluidics/dmf-control-board-firmware
Author: Ryan Fobel and Christian Fobel
Author-email: ryan@fobel.net and christian@fobel.net
License: GPLv2
Platform: UNKNOWN
Requires-Dist: arduino-helpers (>=0.3.post10)
Requires-Dist: arduino-scons
Requires-Dist: arrow
Requires-Dist: decorator
Requires-Dist: functools32
Requires-Dist: matplotlib
Requires-Dist: microdrop-utility
Requires-Dist: pandas (>=0.17)
Requires-Dist: scipy
Requires-Dist: serial-device (>=0.4)
Requires-Dist: svg-model (>=0.5.post20)
Requires-Dist: sympy
Requires-Dist: tables
Requires-Dist: wheeler.base-node (>=0.3.post2)
Provides-Extra: build
Requires-Dist: SCons (>=2.4.1); extra == 'build'
Requires-Dist: arduino-scons (>=v0.1.post11); extra == 'build'
